<?xml version="1.0" ?><annotation>
  <filename>pedestrian12.jpg</filename>
  <object_num>2</object_num>
  <size>
    <width>320</width>
    <height>240</height>
  </size>
  <object>
    <name>pedestrian</name>
    <difficult>0</difficult>
    <bndbox>
      <xmin>127</xmin>
      <ymin>19</ymin>
      <xmax>152</xmax>
      <ymax>62</ymax>
    </bndbox>
  </object>
  <object>
    <name>pedestrian</name>
    <difficult>0</difficult>
    <bndbox>
      <xmin>83</xmin>
      <ymin>8</ymin>
      <xmax>109</xmax>
      <ymax>56</ymax>
    </bndbox>
  </object>
</annotation>
